yummy_rs-0.0.7.dist-info/METADATA
yummy_rs-0.0.7.dist-info/WHEEL
yummy_rs-0.0.7.dist-info/license_files/LICENSE
yummy_rs/__init__.py
yummy_rs/yummy_rs.cpython-39-x86_64-linux-gnu.so
yummy_rs-0.0.7.dist-info/RECORD
