Metadata-Version: 2.1
Name: yummy-rs
Version: 0.0.7
Classifier: Programming Language :: Rust
Classifier: Programming Language :: Python :: Implementation :: CPython
Classifier: Programming Language :: Python :: Implementation :: PyPy
License-File: LICENSE
Summary: Yummy rust extensions
Requires-Python: >=3.7
Project-URL: repository, https://github.com/yummyml/yummy
